examples/__init__.py
examples/quantize_cmd.py
examples/quantize_model_oob_slim.py
examples/quantize_model_zoo.py
examples/quantize_python.py
examples/include/__init__.py
examples/include/datasets2.py
examples/include/eval_image_classifier_optimize.py
examples/include/preprocessing2.py
intel_quantization/__init__.py
intel_quantization/graph_converter.py
intel_quantization/util.py
intel_quantization/quantize_graph/__init__.py
intel_quantization/quantize_graph/quantize_graph_base.py
intel_quantization/quantize_graph/quantize_graph_common.py
intel_quantization/quantize_graph/quantize_graph_concatv2.py
intel_quantization/quantize_graph/quantize_graph_conv.py
intel_quantization/quantize_graph/quantize_graph_for_intel_cpu.py
intel_quantization/quantize_graph/quantize_graph_matmul.py
intel_quantization/quantize_graph/quantize_graph_pad.py
intel_quantization/quantize_graph/quantize_graph_pooling.py
intel_quantization/transform_graph/__init__.py
intel_quantization/transform_graph/fold_batch_norm.py
intel_quantization/transform_graph/fold_old_batchnorm.py
intel_quantization/transform_graph/freeze_max_min.py
intel_quantization/transform_graph/fuse_column_wise_mul.py
intel_quantization/transform_graph/fuse_quantized_conv_and_requantize.py
intel_quantization/transform_graph/fuse_quantized_mul_and_requantize.py
intel_quantization/transform_graph/fuse_quantized_mul_requantize_and_dequantize.py
intel_quantization/transform_graph/graph_transform_base.py
intel_quantization/transform_graph/insert_logging.py
intel_quantization/transform_graph/rerange_quantized_concat.py
intel_quantization/transform_graph/strip_unused.py
models/resnet50/__init__.py
models/resnet50/accuracy.py
models/resnet50/cnn_util.py
models/resnet50/datasets.py
models/resnet50/preprocessing.py
intel_quantization-1.1.dist-info/LICENSE
intel_quantization-1.1.dist-info/METADATA
intel_quantization-1.1.dist-info/WHEEL
intel_quantization-1.1.dist-info/top_level.txt
intel_quantization-1.1.dist-info/RECORD
