Metadata-Version: 2.1
Name: intel-quantization
Version: 1.1
Summary: The Python programming APIs packages for Intel® AI Quantization Tools for Tensorflow*.
Home-page: https://github.com/IntelAI/tools
Author: intel
License: UNKNOWN
Keywords: Intel® AI Quantization Tools for Tensorflow*
Platform: UNKNOWN
Classifier: Development Status :: 5 - Production/Stable
Classifier: License :: OSI Approved :: Apache Software License
Classifier: Operating System :: OS Independent
Classifier: Programming Language :: Python :: 3.4
Classifier: Programming Language :: Python :: 3.5
Classifier: Programming Language :: Python :: 3.6
Classifier: Programming Language :: Python :: 3.7
Requires-Python: >=3.4, !=3.1.*, !=3.2.*, !=3.3.*, <3.8
